[
  {
    "signature": "SimpleLog(boolean enabled,boolean always_traceback)",
    "name": "SimpleLog",
    "containingClass": {
      "qualifiedName": "plume.SimpleLog",
      "name": "SimpleLog",
      "isArray": false
    },
    "targetClass": "plume.SimpleLog",
    "isVarArgs": false,
    "parameters": [
      {
        "type": {
          "qualifiedName": "boolean",
          "name": "boolean",
          "isArray": false
        },
        "name": "enabled"
      },
      {
        "type": {
          "qualifiedName": "boolean",
          "name": "boolean",
          "isArray": false
        },
        "name": "always_traceback"
      }
    ],
    "paramTags": [],
    "throwsTags": []
  },
  {
    "signature": "SimpleLog(boolean enabled)",
    "name": "SimpleLog",
    "containingClass": {
      "qualifiedName": "plume.SimpleLog",
      "name": "SimpleLog",
      "isArray": false
    },
    "targetClass": "plume.SimpleLog",
    "isVarArgs": false,
    "parameters": [
      {
        "type": {
          "qualifiedName": "boolean",
          "name": "boolean",
          "isArray": false
        },
        "name": "enabled"
      }
    ],
    "paramTags": [],
    "throwsTags": []
  },
  {
    "signature": "SimpleLog()",
    "name": "SimpleLog",
    "containingClass": {
      "qualifiedName": "plume.SimpleLog",
      "name": "SimpleLog",
      "isArray": false
    },
    "targetClass": "plume.SimpleLog",
    "isVarArgs": false,
    "parameters": [],
    "paramTags": [],
    "throwsTags": []
  },
  {
    "signature": "SimpleLog(java.lang.String filename,boolean enabled)",
    "name": "SimpleLog",
    "containingClass": {
      "qualifiedName": "plume.SimpleLog",
      "name": "SimpleLog",
      "isArray": false
    },
    "targetClass": "plume.SimpleLog",
    "isVarArgs": false,
    "parameters": [
      {
        "type": {
          "qualifiedName": "java.lang.String",
          "name": "String",
          "isArray": false
        },
        "name": "filename"
      },
      {
        "type": {
          "qualifiedName": "boolean",
          "name": "boolean",
          "isArray": false
        },
        "name": "enabled"
      }
    ],
    "paramTags": [],
    "throwsTags": []
  },
  {
    "signature": "enabled()",
    "name": "enabled",
    "containingClass": {
      "qualifiedName": "plume.SimpleLog",
      "name": "SimpleLog",
      "isArray": false
    },
    "targetClass": "plume.SimpleLog",
    "isVarArgs": false,
    "returnType": {
      "qualifiedName": "boolean",
      "name": "boolean",
      "isArray": false
    },
    "parameters": [],
    "paramTags": [],
    "throwsTags": []
  },
  {
    "signature": "log(java.lang.String format,java.lang.Object[] args)",
    "name": "log",
    "containingClass": {
      "qualifiedName": "plume.SimpleLog",
      "name": "SimpleLog",
      "isArray": false
    },
    "targetClass": "plume.SimpleLog",
    "isVarArgs": true,
    "returnType": {
      "qualifiedName": "void",
      "name": "void",
      "isArray": false
    },
    "parameters": [
      {
        "type": {
          "qualifiedName": "java.lang.String",
          "name": "String",
          "isArray": false
        },
        "name": "format"
      },
      {
        "type": {
          "qualifiedName": "java.lang.Object[]",
          "name": "Object[]",
          "isArray": true,
          "componentType": {
            "qualifiedName": "java.lang.Object",
            "name": "Object",
            "isArray": false
          }
        },
        "name": "args"
      }
    ],
    "paramTags": [
      {
        "parameter": {
          "type": {
            "qualifiedName": "java.lang.String",
            "name": "String",
            "isArray": false
          },
          "name": "format"
        },
        "comment": "format string for message",
        "kind": "PARAM",
        "condition": ""
      },
      {
        "parameter": {
          "type": {
            "qualifiedName": "java.lang.Object[]",
            "name": "Object[]",
            "isArray": true,
            "componentType": {
              "qualifiedName": "java.lang.Object",
              "name": "Object",
              "isArray": false
            }
          },
          "name": "args"
        },
        "comment": "values to be substituted into format",
        "kind": "PARAM",
        "condition": ""
      }
    ],
    "throwsTags": []
  },
  {
    "signature": "log_tb(java.lang.String format,java.lang.Object[] args)",
    "name": "log_tb",
    "containingClass": {
      "qualifiedName": "plume.SimpleLog",
      "name": "SimpleLog",
      "isArray": false
    },
    "targetClass": "plume.SimpleLog",
    "isVarArgs": true,
    "returnType": {
      "qualifiedName": "void",
      "name": "void",
      "isArray": false
    },
    "parameters": [
      {
        "type": {
          "qualifiedName": "java.lang.String",
          "name": "String",
          "isArray": false
        },
        "name": "format"
      },
      {
        "type": {
          "qualifiedName": "java.lang.Object[]",
          "name": "Object[]",
          "isArray": true,
          "componentType": {
            "qualifiedName": "java.lang.Object",
            "name": "Object",
            "isArray": false
          }
        },
        "name": "args"
      }
    ],
    "paramTags": [
      {
        "parameter": {
          "type": {
            "qualifiedName": "java.lang.String",
            "name": "String",
            "isArray": false
          },
          "name": "format"
        },
        "comment": "format string for message",
        "kind": "PARAM",
        "condition": ""
      },
      {
        "parameter": {
          "type": {
            "qualifiedName": "java.lang.Object[]",
            "name": "Object[]",
            "isArray": true,
            "componentType": {
              "qualifiedName": "java.lang.Object",
              "name": "Object",
              "isArray": false
            }
          },
          "name": "args"
        },
        "comment": "values to be substituted into format",
        "kind": "PARAM",
        "condition": ""
      }
    ],
    "throwsTags": []
  },
  {
    "signature": "tb()",
    "name": "tb",
    "containingClass": {
      "qualifiedName": "plume.SimpleLog",
      "name": "SimpleLog",
      "isArray": false
    },
    "targetClass": "plume.SimpleLog",
    "isVarArgs": false,
    "returnType": {
      "qualifiedName": "void",
      "name": "void",
      "isArray": false
    },
    "parameters": [],
    "paramTags": [],
    "throwsTags": []
  },
  {
    "signature": "indent()",
    "name": "indent",
    "containingClass": {
      "qualifiedName": "plume.SimpleLog",
      "name": "SimpleLog",
      "isArray": false
    },
    "targetClass": "plume.SimpleLog",
    "isVarArgs": false,
    "returnType": {
      "qualifiedName": "void",
      "name": "void",
      "isArray": false
    },
    "parameters": [],
    "paramTags": [],
    "throwsTags": []
  },
  {
    "signature": "indent(java.lang.String format,java.lang.Object[] args)",
    "name": "indent",
    "containingClass": {
      "qualifiedName": "plume.SimpleLog",
      "name": "SimpleLog",
      "isArray": false
    },
    "targetClass": "plume.SimpleLog",
    "isVarArgs": true,
    "returnType": {
      "qualifiedName": "void",
      "name": "void",
      "isArray": false
    },
    "parameters": [
      {
        "type": {
          "qualifiedName": "java.lang.String",
          "name": "String",
          "isArray": false
        },
        "name": "format"
      },
      {
        "type": {
          "qualifiedName": "java.lang.Object[]",
          "name": "Object[]",
          "isArray": true,
          "componentType": {
            "qualifiedName": "java.lang.Object",
            "name": "Object",
            "isArray": false
          }
        },
        "name": "args"
      }
    ],
    "paramTags": [],
    "throwsTags": []
  },
  {
    "signature": "clear()",
    "name": "clear",
    "containingClass": {
      "qualifiedName": "plume.SimpleLog",
      "name": "SimpleLog",
      "isArray": false
    },
    "targetClass": "plume.SimpleLog",
    "isVarArgs": false,
    "returnType": {
      "qualifiedName": "void",
      "name": "void",
      "isArray": false
    },
    "parameters": [],
    "paramTags": [],
    "throwsTags": []
  },
  {
    "signature": "clear(java.lang.String format,java.lang.Object[] args)",
    "name": "clear",
    "containingClass": {
      "qualifiedName": "plume.SimpleLog",
      "name": "SimpleLog",
      "isArray": false
    },
    "targetClass": "plume.SimpleLog",
    "isVarArgs": true,
    "returnType": {
      "qualifiedName": "void",
      "name": "void",
      "isArray": false
    },
    "parameters": [
      {
        "type": {
          "qualifiedName": "java.lang.String",
          "name": "String",
          "isArray": false
        },
        "name": "format"
      },
      {
        "type": {
          "qualifiedName": "java.lang.Object[]",
          "name": "Object[]",
          "isArray": true,
          "componentType": {
            "qualifiedName": "java.lang.Object",
            "name": "Object",
            "isArray": false
          }
        },
        "name": "args"
      }
    ],
    "paramTags": [
      {
        "parameter": {
          "type": {
            "qualifiedName": "java.lang.String",
            "name": "String",
            "isArray": false
          },
          "name": "format"
        },
        "comment": "format string for message",
        "kind": "PARAM",
        "condition": ""
      },
      {
        "parameter": {
          "type": {
            "qualifiedName": "java.lang.Object[]",
            "name": "Object[]",
            "isArray": true,
            "componentType": {
              "qualifiedName": "java.lang.Object",
              "name": "Object",
              "isArray": false
            }
          },
          "name": "args"
        },
        "comment": "values to be substituted into format",
        "kind": "PARAM",
        "condition": ""
      }
    ],
    "throwsTags": []
  },
  {
    "signature": "exdent()",
    "name": "exdent",
    "containingClass": {
      "qualifiedName": "plume.SimpleLog",
      "name": "SimpleLog",
      "isArray": false
    },
    "targetClass": "plume.SimpleLog",
    "isVarArgs": false,
    "returnType": {
      "qualifiedName": "void",
      "name": "void",
      "isArray": false
    },
    "parameters": [],
    "paramTags": [],
    "throwsTags": []
  },
  {
    "signature": "exdent_time(java.lang.String format,java.lang.Object[] args)",
    "name": "exdent_time",
    "containingClass": {
      "qualifiedName": "plume.SimpleLog",
      "name": "SimpleLog",
      "isArray": false
    },
    "targetClass": "plume.SimpleLog",
    "isVarArgs": true,
    "returnType": {
      "qualifiedName": "void",
      "name": "void",
      "isArray": false
    },
    "parameters": [
      {
        "type": {
          "qualifiedName": "java.lang.String",
          "name": "String",
          "isArray": false
        },
        "name": "format"
      },
      {
        "type": {
          "qualifiedName": "java.lang.Object[]",
          "name": "Object[]",
          "isArray": true,
          "componentType": {
            "qualifiedName": "java.lang.Object",
            "name": "Object",
            "isArray": false
          }
        },
        "name": "args"
      }
    ],
    "paramTags": [
      {
        "parameter": {
          "type": {
            "qualifiedName": "java.lang.String",
            "name": "String",
            "isArray": false
          },
          "name": "format"
        },
        "comment": "format string for message",
        "kind": "PARAM",
        "condition": ""
      },
      {
        "parameter": {
          "type": {
            "qualifiedName": "java.lang.Object[]",
            "name": "Object[]",
            "isArray": true,
            "componentType": {
              "qualifiedName": "java.lang.Object",
              "name": "Object",
              "isArray": false
            }
          },
          "name": "args"
        },
        "comment": "values to be substituted into format",
        "kind": "PARAM",
        "condition": ""
      }
    ],
    "throwsTags": []
  },
  {
    "signature": "reset_start_time()",
    "name": "reset_start_time",
    "containingClass": {
      "qualifiedName": "plume.SimpleLog",
      "name": "SimpleLog",
      "isArray": false
    },
    "targetClass": "plume.SimpleLog",
    "isVarArgs": false,
    "returnType": {
      "qualifiedName": "void",
      "name": "void",
      "isArray": false
    },
    "parameters": [],
    "paramTags": [],
    "throwsTags": []
  },
  {
    "signature": "push_start_time()",
    "name": "push_start_time",
    "containingClass": {
      "qualifiedName": "plume.SimpleLog",
      "name": "SimpleLog",
      "isArray": false
    },
    "targetClass": "plume.SimpleLog",
    "isVarArgs": false,
    "returnType": {
      "qualifiedName": "void",
      "name": "void",
      "isArray": false
    },
    "parameters": [],
    "paramTags": [],
    "throwsTags": []
  },
  {
    "signature": "pop_start_time()",
    "name": "pop_start_time",
    "containingClass": {
      "qualifiedName": "plume.SimpleLog",
      "name": "SimpleLog",
      "isArray": false
    },
    "targetClass": "plume.SimpleLog",
    "isVarArgs": false,
    "returnType": {
      "qualifiedName": "void",
      "name": "void",
      "isArray": false
    },
    "parameters": [],
    "paramTags": [],
    "throwsTags": []
  },
  {
    "signature": "log_time(java.lang.String format,java.lang.Object[] args)",
    "name": "log_time",
    "containingClass": {
      "qualifiedName": "plume.SimpleLog",
      "name": "SimpleLog",
      "isArray": false
    },
    "targetClass": "plume.SimpleLog",
    "isVarArgs": true,
    "returnType": {
      "qualifiedName": "void",
      "name": "void",
      "isArray": false
    },
    "parameters": [
      {
        "type": {
          "qualifiedName": "java.lang.String",
          "name": "String",
          "isArray": false
        },
        "name": "format"
      },
      {
        "type": {
          "qualifiedName": "java.lang.Object[]",
          "name": "Object[]",
          "isArray": true,
          "componentType": {
            "qualifiedName": "java.lang.Object",
            "name": "Object",
            "isArray": false
          }
        },
        "name": "args"
      }
    ],
    "paramTags": [
      {
        "parameter": {
          "type": {
            "qualifiedName": "java.lang.String",
            "name": "String",
            "isArray": false
          },
          "name": "format"
        },
        "comment": "format string for message",
        "kind": "PARAM",
        "condition": ""
      },
      {
        "parameter": {
          "type": {
            "qualifiedName": "java.lang.Object[]",
            "name": "Object[]",
            "isArray": true,
            "componentType": {
              "qualifiedName": "java.lang.Object",
              "name": "Object",
              "isArray": false
            }
          },
          "name": "args"
        },
        "comment": "values to be substituted into format",
        "kind": "PARAM",
        "condition": ""
      }
    ],
    "throwsTags": []
  }
]