[
  {
    "signature": "getValues()",
    "name": "getValues",
    "containingClass": {
      "qualifiedName": "net.sf.freecol.common.model.TypeCountMap",
      "name": "TypeCountMap",
      "isArray": false
    },
    "targetClass": "net.sf.freecol.common.model.TypeCountMap",
    "isVarArgs": false,
    "returnType": {
      "qualifiedName": "java.util.Map",
      "name": "Map",
      "isArray": false
    },
    "parameters": [],
    "paramTags": [],
    "throwsTags": []
  },
  {
    "signature": "getCount(net.sf.freecol.common.model.FreeColGameObjectType key)",
    "name": "getCount",
    "containingClass": {
      "qualifiedName": "net.sf.freecol.common.model.TypeCountMap",
      "name": "TypeCountMap",
      "isArray": false
    },
    "targetClass": "net.sf.freecol.common.model.TypeCountMap",
    "isVarArgs": false,
    "returnType": {
      "qualifiedName": "int",
      "name": "int",
      "isArray": false
    },
    "parameters": [
      {
        "type": {
          "qualifiedName": "net.sf.freecol.common.model.FreeColGameObjectType",
          "name": "FreeColGameObjectType",
          "isArray": false
        },
        "name": "key"
      }
    ],
    "paramTags": [],
    "throwsTags": []
  },
  {
    "signature": "incrementCount(net.sf.freecol.common.model.FreeColGameObjectType key,int newCount)",
    "name": "incrementCount",
    "containingClass": {
      "qualifiedName": "net.sf.freecol.common.model.TypeCountMap",
      "name": "TypeCountMap",
      "isArray": false
    },
    "targetClass": "net.sf.freecol.common.model.TypeCountMap",
    "isVarArgs": false,
    "returnType": {
      "qualifiedName": "java.lang.Integer",
      "name": "Integer",
      "isArray": false
    },
    "parameters": [
      {
        "type": {
          "qualifiedName": "net.sf.freecol.common.model.FreeColGameObjectType",
          "name": "FreeColGameObjectType",
          "isArray": false
        },
        "name": "key"
      },
      {
        "type": {
          "qualifiedName": "int",
          "name": "int",
          "isArray": false
        },
        "name": "newCount"
      }
    ],
    "paramTags": [],
    "throwsTags": []
  },
  {
    "signature": "add(net.sf.freecol.common.model.TypeCountMap other)",
    "name": "add",
    "containingClass": {
      "qualifiedName": "net.sf.freecol.common.model.TypeCountMap",
      "name": "TypeCountMap",
      "isArray": false
    },
    "targetClass": "net.sf.freecol.common.model.TypeCountMap",
    "isVarArgs": false,
    "returnType": {
      "qualifiedName": "void",
      "name": "void",
      "isArray": false
    },
    "parameters": [
      {
        "type": {
          "qualifiedName": "net.sf.freecol.common.model.TypeCountMap",
          "name": "TypeCountMap",
          "isArray": false
        },
        "name": "other"
      }
    ],
    "paramTags": [],
    "throwsTags": []
  },
  {
    "signature": "clear()",
    "name": "clear",
    "containingClass": {
      "qualifiedName": "net.sf.freecol.common.model.TypeCountMap",
      "name": "TypeCountMap",
      "isArray": false
    },
    "targetClass": "net.sf.freecol.common.model.TypeCountMap",
    "isVarArgs": false,
    "returnType": {
      "qualifiedName": "void",
      "name": "void",
      "isArray": false
    },
    "parameters": [],
    "paramTags": [],
    "throwsTags": []
  },
  {
    "signature": "keySet()",
    "name": "keySet",
    "containingClass": {
      "qualifiedName": "net.sf.freecol.common.model.TypeCountMap",
      "name": "TypeCountMap",
      "isArray": false
    },
    "targetClass": "net.sf.freecol.common.model.TypeCountMap",
    "isVarArgs": false,
    "returnType": {
      "qualifiedName": "java.util.Set",
      "name": "Set",
      "isArray": false
    },
    "parameters": [],
    "paramTags": [],
    "throwsTags": []
  },
  {
    "signature": "values()",
    "name": "values",
    "containingClass": {
      "qualifiedName": "net.sf.freecol.common.model.TypeCountMap",
      "name": "TypeCountMap",
      "isArray": false
    },
    "targetClass": "net.sf.freecol.common.model.TypeCountMap",
    "isVarArgs": false,
    "returnType": {
      "qualifiedName": "java.util.Collection",
      "name": "Collection",
      "isArray": false
    },
    "parameters": [],
    "paramTags": [],
    "throwsTags": []
  },
  {
    "signature": "containsKey(net.sf.freecol.common.model.FreeColGameObjectType key)",
    "name": "containsKey",
    "containingClass": {
      "qualifiedName": "net.sf.freecol.common.model.TypeCountMap",
      "name": "TypeCountMap",
      "isArray": false
    },
    "targetClass": "net.sf.freecol.common.model.TypeCountMap",
    "isVarArgs": false,
    "returnType": {
      "qualifiedName": "boolean",
      "name": "boolean",
      "isArray": false
    },
    "parameters": [
      {
        "type": {
          "qualifiedName": "net.sf.freecol.common.model.FreeColGameObjectType",
          "name": "FreeColGameObjectType",
          "isArray": false
        },
        "name": "key"
      }
    ],
    "paramTags": [],
    "throwsTags": []
  },
  {
    "signature": "isEmpty()",
    "name": "isEmpty",
    "containingClass": {
      "qualifiedName": "net.sf.freecol.common.model.TypeCountMap",
      "name": "TypeCountMap",
      "isArray": false
    },
    "targetClass": "net.sf.freecol.common.model.TypeCountMap",
    "isVarArgs": false,
    "returnType": {
      "qualifiedName": "boolean",
      "name": "boolean",
      "isArray": false
    },
    "parameters": [],
    "paramTags": [],
    "throwsTags": []
  },
  {
    "signature": "size()",
    "name": "size",
    "containingClass": {
      "qualifiedName": "net.sf.freecol.common.model.TypeCountMap",
      "name": "TypeCountMap",
      "isArray": false
    },
    "targetClass": "net.sf.freecol.common.model.TypeCountMap",
    "isVarArgs": false,
    "returnType": {
      "qualifiedName": "int",
      "name": "int",
      "isArray": false
    },
    "parameters": [],
    "paramTags": [],
    "throwsTags": []
  },
  {
    "signature": "putAll(net.sf.freecol.common.model.TypeCountMap other)",
    "name": "putAll",
    "containingClass": {
      "qualifiedName": "net.sf.freecol.common.model.TypeCountMap",
      "name": "TypeCountMap",
      "isArray": false
    },
    "targetClass": "net.sf.freecol.common.model.TypeCountMap",
    "isVarArgs": false,
    "returnType": {
      "qualifiedName": "void",
      "name": "void",
      "isArray": false
    },
    "parameters": [
      {
        "type": {
          "qualifiedName": "net.sf.freecol.common.model.TypeCountMap",
          "name": "TypeCountMap",
          "isArray": false
        },
        "name": "other"
      }
    ],
    "paramTags": [],
    "throwsTags": []
  },
  {
    "signature": "toString()",
    "name": "toString",
    "containingClass": {
      "qualifiedName": "net.sf.freecol.common.model.TypeCountMap",
      "name": "TypeCountMap",
      "isArray": false
    },
    "targetClass": "net.sf.freecol.common.model.TypeCountMap",
    "isVarArgs": false,
    "returnType": {
      "qualifiedName": "java.lang.String",
      "name": "String",
      "isArray": false
    },
    "parameters": [],
    "paramTags": [],
    "throwsTags": []
  }
]