[
  {
    "signature": "value(double x)",
    "name": "value",
    "containingClass": {
      "qualifiedName": "org.apache.commons.math3.analysis.UnivariateVectorFunction",
      "name": "UnivariateVectorFunction",
      "isArray": false
    },
    "targetClass": "org.apache.commons.math3.analysis.UnivariateVectorFunction",
    "isVarArgs": false,
    "returnType": {
      "qualifiedName": "double[]",
      "name": "double[]",
      "isArray": true,
      "componentType": {
        "qualifiedName": "double",
        "name": "double",
        "isArray": false
      }
    },
    "parameters": [
      {
        "type": {
          "qualifiedName": "double",
          "name": "double",
          "isArray": false
        },
        "name": "x"
      }
    ],
    "paramTags": [
      {
        "parameter": {
          "type": {
            "qualifiedName": "double",
            "name": "double",
            "isArray": false
          },
          "name": "x"
        },
        "comment": "the point for which the function value should be computed",
        "kind": "PARAM",
        "condition": ""
      }
    ],
    "returnTag": {
      "comment": "the value",
      "kind": "RETURN",
      "condition": "true ? result.equals(args[0])"
    },
    "throwsTags": []
  }
]