[
  {
    "signature": "LazyMap(java.util.Map map,org.apache.commons.collections4.Factory factory)",
    "name": "LazyMap",
    "containingClass": {
      "qualifiedName": "org.apache.commons.collections4.map.LazyMap",
      "name": "LazyMap",
      "isArray": false
    },
    "targetClass": "org.apache.commons.collections4.map.LazyMap",
    "isVarArgs": false,
    "parameters": [
      {
        "type": {
          "qualifiedName": "java.util.Map",
          "name": "Map",
          "isArray": false
        },
        "name": "map"
      },
      {
        "type": {
          "qualifiedName": "org.apache.commons.collections4.Factory",
          "name": "Factory",
          "isArray": false
        },
        "name": "factory"
      }
    ],
    "paramTags": [
      {
        "parameter": {
          "type": {
            "qualifiedName": "java.util.Map",
            "name": "Map",
            "isArray": false
          },
          "name": "map"
        },
        "comment": "the map to decorate, must not be null",
        "kind": "PARAM",
        "condition": "(args[0]==null) == false"
      },
      {
        "parameter": {
          "type": {
            "qualifiedName": "org.apache.commons.collections4.Factory",
            "name": "Factory",
            "isArray": false
          },
          "name": "factory"
        },
        "comment": "the factory to use, must not be null",
        "kind": "PARAM",
        "condition": "(args[1]==null) == false"
      }
    ],
    "throwsTags": [
      {
        "exception": {
          "qualifiedName": "java.lang.NullPointerException",
          "name": "NullPointerException",
          "isArray": false
        },
        "codeTags": [],
        "comment": "if map or factory is null",
        "kind": "THROWS",
        "condition": "args[0]==null || args[1]==null"
      }
    ]
  },
  {
    "signature": "LazyMap(java.util.Map map,org.apache.commons.collections4.Transformer factory)",
    "name": "LazyMap",
    "containingClass": {
      "qualifiedName": "org.apache.commons.collections4.map.LazyMap",
      "name": "LazyMap",
      "isArray": false
    },
    "targetClass": "org.apache.commons.collections4.map.LazyMap",
    "isVarArgs": false,
    "parameters": [
      {
        "type": {
          "qualifiedName": "java.util.Map",
          "name": "Map",
          "isArray": false
        },
        "name": "map"
      },
      {
        "type": {
          "qualifiedName": "org.apache.commons.collections4.Transformer",
          "name": "Transformer",
          "isArray": false
        },
        "name": "factory"
      }
    ],
    "paramTags": [
      {
        "parameter": {
          "type": {
            "qualifiedName": "java.util.Map",
            "name": "Map",
            "isArray": false
          },
          "name": "map"
        },
        "comment": "the map to decorate, must not be null",
        "kind": "PARAM",
        "condition": "(args[0]==null) == false"
      },
      {
        "parameter": {
          "type": {
            "qualifiedName": "org.apache.commons.collections4.Transformer",
            "name": "Transformer",
            "isArray": false
          },
          "name": "factory"
        },
        "comment": "the factory to use, must not be null",
        "kind": "PARAM",
        "condition": "(args[1]==null) == false"
      }
    ],
    "throwsTags": [
      {
        "exception": {
          "qualifiedName": "java.lang.NullPointerException",
          "name": "NullPointerException",
          "isArray": false
        },
        "codeTags": [],
        "comment": "if map or factory is null",
        "kind": "THROWS",
        "condition": "args[0]==null || args[1]==null"
      }
    ]
  },
  {
    "signature": "lazyMap(java.util.Map map,org.apache.commons.collections4.Factory factory)",
    "name": "lazyMap",
    "containingClass": {
      "qualifiedName": "org.apache.commons.collections4.map.LazyMap",
      "name": "LazyMap",
      "isArray": false
    },
    "targetClass": "org.apache.commons.collections4.map.LazyMap",
    "isVarArgs": false,
    "returnType": {
      "qualifiedName": "org.apache.commons.collections4.map.LazyMap",
      "name": "LazyMap",
      "isArray": false
    },
    "parameters": [
      {
        "type": {
          "qualifiedName": "java.util.Map",
          "name": "Map",
          "isArray": false
        },
        "name": "map"
      },
      {
        "type": {
          "qualifiedName": "org.apache.commons.collections4.Factory",
          "name": "Factory",
          "isArray": false
        },
        "name": "factory"
      }
    ],
    "paramTags": [
      {
        "parameter": {
          "type": {
            "qualifiedName": "java.util.Map",
            "name": "Map",
            "isArray": false
          },
          "name": "map"
        },
        "comment": "the map to decorate, must not be null",
        "kind": "PARAM",
        "condition": "(args[0]==null) == false"
      },
      {
        "parameter": {
          "type": {
            "qualifiedName": "org.apache.commons.collections4.Factory",
            "name": "Factory",
            "isArray": false
          },
          "name": "factory"
        },
        "comment": "the factory to use, must not be null",
        "kind": "PARAM",
        "condition": "(args[1]==null) == false"
      }
    ],
    "returnTag": {
      "comment": "a new lazy map",
      "kind": "RETURN",
      "condition": ""
    },
    "throwsTags": [
      {
        "exception": {
          "qualifiedName": "java.lang.NullPointerException",
          "name": "NullPointerException",
          "isArray": false
        },
        "codeTags": [],
        "comment": "if map or factory is null",
        "kind": "THROWS",
        "condition": "args[0]==null || args[1]==null"
      }
    ]
  },
  {
    "signature": "lazyMap(java.util.Map map,org.apache.commons.collections4.Transformer factory)",
    "name": "lazyMap",
    "containingClass": {
      "qualifiedName": "org.apache.commons.collections4.map.LazyMap",
      "name": "LazyMap",
      "isArray": false
    },
    "targetClass": "org.apache.commons.collections4.map.LazyMap",
    "isVarArgs": false,
    "returnType": {
      "qualifiedName": "org.apache.commons.collections4.map.LazyMap",
      "name": "LazyMap",
      "isArray": false
    },
    "parameters": [
      {
        "type": {
          "qualifiedName": "java.util.Map",
          "name": "Map",
          "isArray": false
        },
        "name": "map"
      },
      {
        "type": {
          "qualifiedName": "org.apache.commons.collections4.Transformer",
          "name": "Transformer",
          "isArray": false
        },
        "name": "factory"
      }
    ],
    "paramTags": [
      {
        "parameter": {
          "type": {
            "qualifiedName": "java.util.Map",
            "name": "Map",
            "isArray": false
          },
          "name": "map"
        },
        "comment": "the map to decorate, must not be null",
        "kind": "PARAM",
        "condition": "(args[0]==null) == false"
      },
      {
        "parameter": {
          "type": {
            "qualifiedName": "org.apache.commons.collections4.Transformer",
            "name": "Transformer",
            "isArray": false
          },
          "name": "factory"
        },
        "comment": "the factory to use, must not be null",
        "kind": "PARAM",
        "condition": "(args[1]==null) == false"
      }
    ],
    "returnTag": {
      "comment": "a new lazy map",
      "kind": "RETURN",
      "condition": ""
    },
    "throwsTags": [
      {
        "exception": {
          "qualifiedName": "java.lang.NullPointerException",
          "name": "NullPointerException",
          "isArray": false
        },
        "codeTags": [],
        "comment": "if map or factory is null",
        "kind": "THROWS",
        "condition": "args[0]==null || args[1]==null"
      }
    ]
  },
  {
    "signature": "get(java.lang.Object key)",
    "name": "get",
    "containingClass": {
      "qualifiedName": "org.apache.commons.collections4.map.LazyMap",
      "name": "LazyMap",
      "isArray": false
    },
    "targetClass": "org.apache.commons.collections4.map.LazyMap",
    "isVarArgs": false,
    "returnType": {
      "qualifiedName": "V",
      "name": "V",
      "isArray": false
    },
    "parameters": [
      {
        "type": {
          "qualifiedName": "java.lang.Object",
          "name": "Object",
          "isArray": false
        },
        "name": "key"
      }
    ],
    "paramTags": [],
    "throwsTags": []
  }
]